<rpc-reply semp-version="soltr/8_2_0">
  <rpc>
    <show>
      <redundancy>
        <config-status>Enabled</config-status>
        <redundancy-status>Up</redundancy-status>
        <last-failure-reason>Primary IP is not configured</last-failure-reason>
        <last-failure-time>Jan  4 2019 21:32:07 EST</last-failure-time>
        <operating-mode>Message Routing Node</operating-mode>
        <switchover-mechanism>IP Address Takeover</switchover-mechanism>
        <auto-revert>false</auto-revert>
        <redundancy-mode>Active/Standby</redundancy-mode>
        <active-standby-role>Primary</active-standby-role>
        <mate-router-name>lab-129-60</mate-router-name>
        <mate-connect-via-addr></mate-connect-via-addr>
        <oper-status>
          <adb-link-up>true</adb-link-up>
          <adb-link-last-failure-reason>N/A</adb-link-last-failure-reason>
          <adb-link-last-failure-time>Dec 31 1969 19:00:00 EST</adb-link-last-failure-time>
          <adb-hello-up>true</adb-hello-up>
          <adb-hello-last-failure-reason>N/A</adb-hello-last-failure-reason>
          <adb-hello-last-failure-time>Dec 31 1969 19:00:00 EST</adb-hello-last-failure-time>
          <adb-hello-avg-latency>0</adb-hello-avg-latency>
          <adb-hello-max-latency>0</adb-hello-max-latency>
        </oper-status>
        <adb-hello-interval>1000</adb-hello-interval>
        <adb-hello-timeout>3000</adb-hello-timeout>
        <virtual-routers>
          <primary>
            <config>
              <routing-interface>1/6/lag1:1</routing-interface>
              <vrrp-vrid>115</vrrp-vrid>
            </config>
            <status>
              <activity>Local Active</activity>
              <vrrp>Master</vrrp>
              <routing-interface>Up</routing-interface>
              <vrrp-priority>250</vrrp-priority>
              <detail>
                <priority-reported-by-mate>
                  <summary>Standby</summary>
                  <cspf>None</cspf>
                  <adb-hello>Standby</adb-hello>
                  <vrrp>None (-1)</vrrp>
                </priority-reported-by-mate>
                <activity-status>
                  <summary>Local Active</summary>
                  <operational-status>
                    <summary>Ready</summary>
                    <redundancy-config>Enabled</redundancy-config>
                    <message-spool>Ready</message-spool>
                  </operational-status>
                  <smrp-status>
                    <summary>Ready</summary>
                    <db-build>Ready</db-build>
                    <db-build-percentage>100</db-build-percentage>
                    <db-sync>Ready</db-sync>
                  </smrp-status>
                  <internal>
                    <priority>Active</priority>
                    <activity>Local Active</activity>
                    <redundancy>Pri-Active</redundancy>
                  </internal>
                </activity-status>
                <message-spool-status>
                  <summary>Ready</summary>
                  <message-spool-config>Enabled</message-spool-config>
                  <status-if-enabled>
                    <cvrid-config-ready>true</cvrid-config-ready>
                    <adm-card-ready>true</adm-card-ready>
                    <flash-module-ready>true</flash-module-ready>
                    <power-module-ready>true</power-module-ready>
                    <adm-contents-ready>true</adm-contents-ready>
                    <local-contents-key>192.168.160.115:7,4</local-contents-key>
                    <mate-contents-key>192.168.160.115:7,4</mate-contents-key>
                    <router-schema-match>true</router-schema-match>
                    <disk-ready>true</disk-ready>
                    <disk-contents>Ready</disk-contents>
                    <disk-key-primary>192.168.160.115:7,4</disk-key-primary>
                    <disk-key-backup>192.168.160.115:5,4</disk-key-backup>
                    <adm-datapath-ready>true</adm-datapath-ready>
                    <lock-owner></lock-owner>
                  </status-if-enabled>
                  <internal>
                    <redundancy>AD-Active</redundancy>
                  </internal>
                </message-spool-status>
                <last-update-status>
                  <code>Ok</code>
                  <subscriber></subscriber>
                  <reason></reason>
                </last-update-status>
              </detail>
            </status>
          </primary>
          <backup>
            <config>
              <routing-interface></routing-interface>
              <vrrp-vrid>-1</vrrp-vrid>
            </config>
            <status>
              <activity>Shutdown</activity>
            </status>
          </backup>
        </virtual-routers>
        <mismatch-info>
          <local>
            <primary-cvrid>
              <ip-address>192.168.160.115</ip-address>
            </primary-cvrid>
            <backup-cvrid>
            </backup-cvrid>
            <mate-address>
            </mate-address>
            <ad-enabled-cvrid>
              <ip-address>192.168.160.115</ip-address>
            </ad-enabled-cvrid>
            <disk-wwn>60:06:01:60:40:40:12:00:1c:f9:25:30:3b:6c:dc:11</disk-wwn>
          </local>
          <received-from-mate>
            <primary-cvrid>
              <ip-address>192.168.160.115</ip-address>
            </primary-cvrid>
            <backup-cvrid>
              <ip-address>0.0.0.0</ip-address>
            </backup-cvrid>
            <mate-address>
              <ip-address>192.168.168.60</ip-address>
            </mate-address>
            <ad-enabled-cvrid>
              <ip-address>192.168.160.115</ip-address>
            </ad-enabled-cvrid>
            <disk-wwn>60:06:01:60:40:40:12:00:1c:f9:25:30:3b:6c:dc:11</disk-wwn>
          </received-from-mate>
        </mismatch-info>
      </redundancy>
    </show>
  </rpc>
<execute-result code="ok"/>
</rpc-reply>